nginx/__init__.py
nginx/config/__init__.py
nginx/config/common.py
nginx/config/helpers.py
nginx/config/headers/__init__.py
nginx/config/headers/uwsgi_param.py
nginx/config/api/options.py
nginx/config/api/__init__.py
nginx/config/api/blocks.py
nginx/config/api/base.py
nginx/config/builder/plugins.py
nginx/config/builder/__init__.py
nginx/config/builder/exceptions.py
nginx/config/builder/baseplugins.py
nginx_config_builder-1.0.1.dist-info/RECORD
nginx_config_builder-1.0.1.dist-info/metadata.json
nginx_config_builder-1.0.1.dist-info/WHEEL
nginx_config_builder-1.0.1.dist-info/DESCRIPTION.rst
nginx_config_builder-1.0.1.dist-info/top_level.txt
nginx_config_builder-1.0.1.dist-info/METADATA
