Metadata-Version: 2.0
Name: nginx-config-builder
Version: 1.0.1
Summary: A python library for generating nginx configs.
Home-page: https://github.com/linkedin/nginx-config-builder
Author: Loren M. Carvalho
Author-email: loren@linkedin.com
License: BSD license
Keywords: nginx-config-builder
Platform: UNKNOWN
Classifier: License :: OSI Approved :: BSD License
Classifier: Programming Language :: Python :: 2
Classifier: Programming Language :: Python :: 2.7
Classifier: Programming Language :: Python :: 3
Classifier: Programming Language :: Python :: 3.5
Classifier: Programming Language :: Python :: 3.6
Requires-Dist: six (>=1.10.0)
Requires-Dist: enum34 (==1.1.6)
